antiblock_selenium/__init__.py
antiblock_selenium/camouflage_handler.py
antiblock_selenium/chrome.py
antiblock_selenium/firefox.py
antiblock_selenium/tor_controller.py
antiblock_selenium-0.0.3.dist-info/LICENSE
antiblock_selenium-0.0.3.dist-info/METADATA
antiblock_selenium-0.0.3.dist-info/WHEEL
antiblock_selenium-0.0.3.dist-info/top_level.txt
antiblock_selenium-0.0.3.dist-info/RECORD
